yandex_delivery/__init__.py
yandex_delivery/client.py
yandex_delivery/enums.py
yandex_delivery/exceptions.py
yandex_delivery/objects.py
yandex_delivery_sdk-0.1.4.dist-info/LICENSE
yandex_delivery_sdk-0.1.4.dist-info/METADATA
yandex_delivery_sdk-0.1.4.dist-info/WHEEL
yandex_delivery_sdk-0.1.4.dist-info/RECORD
